DisNet.py
__init__.py
DisNet/DisNet.py
DisNet/__init__.py
DisNet-1.0.dist-info/METADATA
DisNet-1.0.dist-info/WHEEL
DisNet-1.0.dist-info/top_level.txt
DisNet-1.0.dist-info/RECORD
