Metadata-Version: 2.1
Name: DisNet
Version: 1.0
Summary: A Discord bot package
Author: WallCompany
Classifier: Programming Language :: Python :: 3
Classifier: License :: OSI Approved :: MIT License
Classifier: Operating System :: OS Independent
Requires-Dist: discord
